bloxflip/__init__.py
bloxflip/authorization.py
bloxflip/crash.py
bloxflip/currency.py
bloxflip/jackpot.py
bloxflip/mines.py
bloxflip/towers.py
bloxfliptest.py-1.0.0.dist-info/LICENSE
bloxfliptest.py-1.0.0.dist-info/METADATA
bloxfliptest.py-1.0.0.dist-info/WHEEL
bloxfliptest.py-1.0.0.dist-info/top_level.txt
bloxfliptest.py-1.0.0.dist-info/RECORD
