Metadata-Version: 2.1
Name: bloxfliptest.py
Version: 1.0.0
Summary: An api wrapper for https://bloxflip.com
Author: Master
License-File: LICENSE
